LICENSE.txt
MANIFEST.in
NOTICE
setup.py
pingspice/__init__.py
pingspice/errors.py
pingspice/util.py
pingspice.egg-info/PKG-INFO
pingspice.egg-info/SOURCES.txt
pingspice.egg-info/dependency_links.txt
pingspice.egg-info/entry_points.txt
pingspice.egg-info/not-zip-safe
pingspice.egg-info/requires.txt
pingspice.egg-info/top_level.txt
pingspice/analysis/__init__.py
pingspice/analysis/capacitance.py
pingspice/analysis/constraints.py
pingspice/analysis/diode.py
pingspice/analysis/evaluate.py
pingspice/analysis/expressions.py
pingspice/analysis/fixture.py
pingspice/analysis/mosfet.py
pingspice/analysis/mosfet_analyzers.py
pingspice/analysis/mosfet_model.py
pingspice/analysis/msim.py
pingspice/analysis/names.py
pingspice/analysis/param.py
pingspice/analysis/plot.py
pingspice/analysis/psim.py
pingspice/analysis/sim.py
pingspice/analysis/solver.py
pingspice/analysis/sse.py
pingspice/analysis/thermal.py
pingspice/analysis/timing.py
pingspice/analysis/tools.py
pingspice/analysis/vectors.py
pingspice/analysis/wire.py
pingspice/examples/__init__.py
pingspice/examples/boost.py
pingspice/examples/current-limit.py
pingspice/examples/inductor-fixture.py
pingspice/examples/opamp-01.py
pingspice/examples/rlc-01.py
pingspice/examples/rlc-02.py
pingspice/examples/rlc-03.py
pingspice/examples/rlc-04.py
pingspice/examples/rlc-05.py
pingspice/examples/rlc-06.py
pingspice/lib/FQP32N20C.goals
pingspice/lib/IRF9Z34NPbF.goals
pingspice/lib/IXT26P20.goals
pingspice/lib/IXTH130N10T.goals
pingspice/lib/MBR40250.goals
pingspice/lib/MUR420.goals
pingspice/lib/PSMN9R5_100PS.goals
pingspice/lib/RFP12N10L.goals
pingspice/lib/ST75NF20.goals
pingspice/lib/STP60NF06.goals
pingspice/lib/TO220.goals
pingspice/lib/TO220F.goals
pingspice/lib/TO247.goals
pingspice/lib/__init__.py
pingspice/lib/active.py
pingspice/lib/ad.py
pingspice/lib/current.py
pingspice/lib/diodes.py
pingspice/lib/mcp.py
pingspice/lib/mosfets.py
pingspice/lib/passive.py
pingspice/lib/pv.py
pingspice/lib/semiconductor.py
pingspice/lib/thermal.py
pingspice/scripts/__init__.py
pingspice/scripts/examples.py
pingspice/scripts/paramfind.py
pingspice/scripts/ps2sc.py
pingspice/scripts/readcsv.py
pingspice/test/__init__.py
pingspice/test/rc.cir
pingspice/test/testbase.py