Metadata-Version: 1.2
Name: pingspice
Version: 0.4.2
Summary:  Object-oriented netlist construction and multiprocess SPICE simulation. 
Home-page: http://edsuom.com/pingspice.html
Author: Edwin A. Suominen
Author-email: foss@edsuom.com
Maintainer: Edwin A. Suominen
Maintainer-email: foss@edsuom.com
License: Apache License (2.0)
Keywords: Ngspice,spice,eda,Twisted,asynchronous,simulation,electronic,netlist
Platform: OS Independent
Classifier: Development Status :: 4 - Beta
Classifier: Intended Audience :: Developers
Classifier: Intended Audience :: Science/Research
Classifier: License :: OSI Approved :: Apache Software License
Classifier: Operating System :: OS Independent
Classifier: Programming Language :: Python
Classifier: Framework :: Twisted
Classifier: Topic :: Software Development :: Libraries :: Python Modules
